{
  "municipality": "Sariaya",
  "province": "Quezon",
  "region": "Region IV-A (CALABARZON)",
  "psgc_municipality_code": "045645000",
  "barangays": [
    { "code": "045645001", "name": "Antipolo" },
    { "code": "045645002", "name": "Baguio" },
    { "code": "045645003", "name": "Balubal" },
    { "code": "045645004", "name": "Bignay 1" },
    { "code": "045645005", "name": "Bignay 2" },
    { "code": "045645006", "name": "Bucal" },
    { "code": "045645007", "name": "Canda" },
    { "code": "045645008", "name": "Castañas" },
    { "code": "045645009", "name": "Concepcion Banahaw" },
    { "code": "045645010", "name": "Concepcion Pinagbakuran" },
    { "code": "045645011", "name": "Gibanga" },
    { "code": "045645012", "name": "Guisguis-San Roque" },
    { "code": "045645013", "name": "Guisguis-Talon" },
    { "code": "045645014", "name": "Janagdong 1" },
    { "code": "045645015", "name": "Janagdong 2" },
    { "code": "045645016", "name": "Lipot" },
    { "code": "045645017", "name": "Lumangbayan" },
    { "code": "045645018", "name": "Magsaysay" },
    { "code": "045645019", "name": "Mamala 1" },
    { "code": "045645020", "name": "Mamala 2" },
    { "code": "045645021", "name": "Mangayao" },
    { "code": "045645022", "name": "Monserrat" },
    { "code": "045645023", "name": "Morong" },
    { "code": "045645024", "name": "Pili" },
    { "code": "045645025", "name": "Sampaloc 1" },
    { "code": "045645026", "name": "Sampaloc 2" },
    { "code": "045645027", "name": "San Isidro" },
    { "code": "045645028", "name": "San Jose" },
    { "code": "045645029", "name": "San Roque" },
    { "code": "045645030", "name": "Talaan Aplaya" },
    { "code": "045645031", "name": "Talaan-Pantoc" },
    { "code": "045645032", "name": "Talaan-Silangan" },
    { "code": "045645033", "name": "Talayang" },
    { "code": "045645034", "name": "Tumbaga 1" },
    { "code": "045645035", "name": "Tumbaga 2" },
    { "code": "045645036", "name": "Santo Cristo" },
    { "code": "045645037", "name": "Poblacion 1" },
    { "code": "045645038", "name": "Poblacion 2" },
    { "code": "045645039", "name": "Poblacion 3" },
    { "code": "045645040", "name": "Poblacion 4" },
    { "code": "045645041", "name": "Poblacion 5" },
    { "code": "045645042", "name": "Poblacion 6" },
    { "code": "045645043", "name": "Poblacion 7" }
  ]
}
